{
  "m200": {
    "response": {
      "message": "OK",
      "code": 200
    },
    "status": 200,
    "description": "ok reply"
  },
  "m101": {
    "response": {
      "error": "admin Authentication Failed",
      "code": 101
    },
    "status": 401,
    "description": "user failed to provide right admin authorization"
  },
  "m102": {
    "response": {
      "error": "error while processing your request, please try again later",
      "code": 102
    },
    "status": 400,
    "description": "some issue with mongodb"
  },
  "m103": {
    "response": {
      "error": "channel already exists",
      "code": 103
    },
    "status": 422,
    "description": "channel already exists"
  },
  "m104": {
    "response": {
      "error": "channel does not exists",
      "code": 104
    },
    "status": 422,
    "description": "channel does not exists"
  },
  "m105": {
    "response": {
      "error": "missing channel in headers",
      "code": 105
    },
    "status": 412,
    "description": "missing channel in headers"
  }
}